[{"__symbolic":"module","version":3,"metadata":{"GW_SELECT_VALUE_ACCESSOR":{"provide":{"__symbolic":"reference","module":"@angular/forms","name":"NG_VALUE_ACCESSOR"},"useExisting":{"__symbolic":"reference","name":"GWMultiSelectComponent"},"multi":true},"GWMultiSelectComponent":{"__symbolic":"class","extends":{"__symbolic":"reference","module":"../utils/gw-control","name":"GWControl"},"decorators":[{"__symbolic":"call","expression":{"__symbolic":"reference","module":"@angular/core","name":"Component"},"arguments":[{"selector":"gw-multi-select","styleUrls":["./multi-select.component.css"],"templateUrl":"./multi-select.component.html","providers":[{"__symbolic":"reference","name":"GW_SELECT_VALUE_ACCESSOR"}]}]}],"members":{"popover":[{"__symbolic":"property","decorators":[{"__symbolic":"call","expression":{"__symbolic":"reference","module":"@angular/core","name":"ViewChild"},"arguments":[{"__symbolic":"reference","module":"ngx-bootstrap","name":"PopoverDirective"}]}]}],"onSelectEvent":[{"__symbolic":"property","decorators":[{"__symbolic":"call","expression":{"__symbolic":"reference","module":"@angular/core","name":"Output"},"arguments":["onSelect"]}]}],"_data":[{"__symbolic":"property","decorators":[{"__symbolic":"call","expression":{"__symbolic":"reference","module":"@angular/core","name":"Input"},"arguments":["data"]}]}],"clear":[{"__symbolic":"method"}],"updateNgModel":[{"__symbolic":"method"}],"save":[{"__symbolic":"method"}],"cancel":[{"__symbolic":"method"}],"remove":[{"__symbolic":"method"}],"writeValue":[{"__symbolic":"method"}],"refreshUI":[{"__symbolic":"method"}],"registerOnChange":[{"__symbolic":"method"}],"registerOnTouched":[{"__symbolic":"method"}]}}}},{"__symbolic":"module","version":1,"metadata":{"GW_SELECT_VALUE_ACCESSOR":{"provide":{"__symbolic":"reference","module":"@angular/forms","name":"NG_VALUE_ACCESSOR"},"useExisting":{"__symbolic":"reference","name":"GWMultiSelectComponent"},"multi":true},"GWMultiSelectComponent":{"__symbolic":"class","extends":{"__symbolic":"reference","module":"../utils/gw-control","name":"GWControl"},"decorators":[{"__symbolic":"call","expression":{"__symbolic":"reference","module":"@angular/core","name":"Component"},"arguments":[{"selector":"gw-multi-select","styleUrls":["./multi-select.component.css"],"templateUrl":"./multi-select.component.html","providers":[{"__symbolic":"reference","name":"GW_SELECT_VALUE_ACCESSOR"}]}]}],"members":{"popover":[{"__symbolic":"property","decorators":[{"__symbolic":"call","expression":{"__symbolic":"reference","module":"@angular/core","name":"ViewChild"},"arguments":[{"__symbolic":"reference","module":"ngx-bootstrap","name":"PopoverDirective"}]}]}],"onSelectEvent":[{"__symbolic":"property","decorators":[{"__symbolic":"call","expression":{"__symbolic":"reference","module":"@angular/core","name":"Output"},"arguments":["onSelect"]}]}],"_data":[{"__symbolic":"property","decorators":[{"__symbolic":"call","expression":{"__symbolic":"reference","module":"@angular/core","name":"Input"},"arguments":["data"]}]}],"clear":[{"__symbolic":"method"}],"updateNgModel":[{"__symbolic":"method"}],"save":[{"__symbolic":"method"}],"cancel":[{"__symbolic":"method"}],"remove":[{"__symbolic":"method"}],"writeValue":[{"__symbolic":"method"}],"refreshUI":[{"__symbolic":"method"}],"registerOnChange":[{"__symbolic":"method"}],"registerOnTouched":[{"__symbolic":"method"}]}}}}]